MANIFEST.in
setup.py
nbashots/__init__.py
nbashots/api.py
nbashots/charts.py
nbashots.egg-info/PKG-INFO
nbashots.egg-info/SOURCES.txt
nbashots.egg-info/dependency_links.txt
nbashots.egg-info/requires.txt
nbashots.egg-info/top_level.txt